reinstate_revert_revert/__init__.py
reinstate_revert_revert/cli.py
reinstate_revert_revert/parser.py
reinstate_revert_revert-1.0.3.dist-info/entry_points.txt
reinstate_revert_revert-1.0.3.dist-info/LICENSE
reinstate_revert_revert-1.0.3.dist-info/WHEEL
reinstate_revert_revert-1.0.3.dist-info/METADATA
reinstate_revert_revert-1.0.3.dist-info/RECORD
